JSSEnv/__init__.py
JSSEnv/dispatching.py
JSSEnv/utils.py
JSSEnv/envs/__init__.py
JSSEnv/envs/jss_env.py
JSSEnv/envs/registry.py
JSSEnv/envs/instances/dmu16
JSSEnv/envs/instances/dmu17
JSSEnv/envs/instances/dmu18
JSSEnv/envs/instances/dmu19
JSSEnv/envs/instances/dmu20
JSSEnv/envs/instances/ta01
JSSEnv/envs/instances/ta02
JSSEnv/envs/instances/ta03
JSSEnv/envs/instances/ta04
JSSEnv/envs/instances/ta05
JSSEnv/envs/instances/ta06
JSSEnv/envs/instances/ta07
JSSEnv/envs/instances/ta08
JSSEnv/envs/instances/ta09
JSSEnv/envs/instances/ta10
JSSEnv/envs/instances/ta11
JSSEnv/envs/instances/ta12
JSSEnv/envs/instances/ta13
JSSEnv/envs/instances/ta14
JSSEnv/envs/instances/ta15
JSSEnv/envs/instances/ta16
JSSEnv/envs/instances/ta17
JSSEnv/envs/instances/ta18
JSSEnv/envs/instances/ta19
JSSEnv/envs/instances/ta20
JSSEnv/envs/instances/ta21
JSSEnv/envs/instances/ta22
JSSEnv/envs/instances/ta23
JSSEnv/envs/instances/ta24
JSSEnv/envs/instances/ta25
JSSEnv/envs/instances/ta26
JSSEnv/envs/instances/ta27
JSSEnv/envs/instances/ta28
JSSEnv/envs/instances/ta29
JSSEnv/envs/instances/ta30
JSSEnv/envs/instances/ta31
JSSEnv/envs/instances/ta32
JSSEnv/envs/instances/ta33
JSSEnv/envs/instances/ta34
JSSEnv/envs/instances/ta35
JSSEnv/envs/instances/ta36
JSSEnv/envs/instances/ta37
JSSEnv/envs/instances/ta38
JSSEnv/envs/instances/ta39
JSSEnv/envs/instances/ta40
JSSEnv/envs/instances/ta41
JSSEnv/envs/instances/ta42
JSSEnv/envs/instances/ta43
JSSEnv/envs/instances/ta44
JSSEnv/envs/instances/ta45
JSSEnv/envs/instances/ta46
JSSEnv/envs/instances/ta47
JSSEnv/envs/instances/ta48
JSSEnv/envs/instances/ta49
JSSEnv/envs/instances/ta50
JSSEnv/envs/instances/ta51
JSSEnv/envs/instances/ta52
JSSEnv/envs/instances/ta53
JSSEnv/envs/instances/ta54
JSSEnv/envs/instances/ta55
JSSEnv/envs/instances/ta56
JSSEnv/envs/instances/ta57
JSSEnv/envs/instances/ta58
JSSEnv/envs/instances/ta59
JSSEnv/envs/instances/ta60
JSSEnv/envs/instances/ta61
JSSEnv/envs/instances/ta62
JSSEnv/envs/instances/ta63
JSSEnv/envs/instances/ta64
jssenv-1.1.0.dist-info/licenses/LICENSE
jssenv-1.1.0.dist-info/METADATA
jssenv-1.1.0.dist-info/WHEEL
jssenv-1.1.0.dist-info/top_level.txt
jssenv-1.1.0.dist-info/RECORD
